flask_appbuilder/__init__.py
flask_appbuilder/_compat.py
flask_appbuilder/actions.py
flask_appbuilder/base.py
flask_appbuilder/basemanager.py
flask_appbuilder/baseviews.py
flask_appbuilder/cli.py
flask_appbuilder/console.py
flask_appbuilder/const.py
flask_appbuilder/exceptions.py
flask_appbuilder/fields.py
flask_appbuilder/fieldwidgets.py
flask_appbuilder/filemanager.py
flask_appbuilder/filters.py
flask_appbuilder/forms.py
flask_appbuilder/hooks.py
flask_appbuilder/menu.py
flask_appbuilder/messages.py
flask_appbuilder/upload.py
flask_appbuilder/urltools.py
flask_appbuilder/validators.py
flask_appbuilder/views.py
flask_appbuilder/widgets.py
flask_appbuilder/api/__init__.py
flask_appbuilder/api/convert.py
flask_appbuilder/api/manager.py
flask_appbuilder/api/schemas.py
flask_appbuilder/babel/__init__.py
flask_appbuilder/babel/manager.py
flask_appbuilder/babel/views.py
flask_appbuilder/charts/__init__.py
flask_appbuilder/charts/jsontools.py
flask_appbuilder/charts/views.py
flask_appbuilder/charts/widgets.py
flask_appbuilder/models/__init__.py
flask_appbuilder/models/base.py
flask_appbuilder/models/decorators.py
flask_appbuilder/models/filters.py
flask_appbuilder/models/group.py
flask_appbuilder/models/mixins.py
flask_appbuilder/models/generic/__init__.py
flask_appbuilder/models/generic/filters.py
flask_appbuilder/models/generic/interface.py
flask_appbuilder/models/mongoengine/__init__.py
flask_appbuilder/models/mongoengine/fields.py
flask_appbuilder/models/mongoengine/filters.py
flask_appbuilder/models/mongoengine/interface.py
flask_appbuilder/models/sqla/__init__.py
flask_appbuilder/models/sqla/filters.py
flask_appbuilder/models/sqla/interface.py
flask_appbuilder/security/__init__.py
flask_appbuilder/security/api.py
flask_appbuilder/security/decorators.py
flask_appbuilder/security/forms.py
flask_appbuilder/security/manager.py
flask_appbuilder/security/registerviews.py
flask_appbuilder/security/schemas.py
flask_appbuilder/security/views.py
Flask_AppBuilder_jack-3.3.4.dist-info/LICENSE
Flask_AppBuilder_jack-3.3.4.dist-info/METADATA
Flask_AppBuilder_jack-3.3.4.dist-info/WHEEL
Flask_AppBuilder_jack-3.3.4.dist-info/entry_points.txt
Flask_AppBuilder_jack-3.3.4.dist-info/top_level.txt
Flask_AppBuilder_jack-3.3.4.dist-info/RECORD
