Metadata-Version: 2.1
Name: Flask-AppBuilder-jack
Version: 3.3.4
Summary: Simple and rapid application development framework, built on top of Flask. includes detailed security, auto CRUD generation for your models, google charts and much more.
Home-page: https://github.com/jfrag1/flask-appbuilder/
Author: Daniel Vaz Gaspar
Author-email: danielvazgaspar@gmail.com
License: BSD
Platform: any
Classifier: Development Status :: 5 - Production/Stable
Classifier: Environment :: Web Environment
Classifier: Intended Audience :: Developers
Classifier: License :: OSI Approved :: BSD License
Classifier: Operating System :: OS Independent
Classifier: Programming Language :: Python
Classifier: Programming Language :: Python :: 3.6
Classifier: Programming Language :: Python :: 3.7
Classifier: Topic :: Software Development :: Libraries :: Python Modules
Requires-Python: ~=3.6
Requires-Dist: apispec[yaml] (<4,>=3.3)
Requires-Dist: colorama (<1,>=0.3.9)
Requires-Dist: click (<9,>=6.7)
Requires-Dist: email-validator (<2,>=1.0.5)
Requires-Dist: Flask (<2,>=0.12)
Requires-Dist: Flask-Babel (<3,>=1)
Requires-Dist: Flask-Login (<0.5,>=0.3)
Requires-Dist: Flask-OpenID (<2,>=1.2.5)
Requires-Dist: SQLAlchemy (<1.4.0)
Requires-Dist: Flask-SQLAlchemy (<3,>=2.4)
Requires-Dist: Flask-WTF (<0.15.0,>=0.14.2)
Requires-Dist: Flask-JWT-Extended (<4,>=3.18)
Requires-Dist: jsonschema (<4,>=3.0.1)
Requires-Dist: marshmallow (<4,>=3)
Requires-Dist: marshmallow-enum (<2,>=1.5.1)
Requires-Dist: marshmallow-sqlalchemy (<0.27.0,>=0.22.0)
Requires-Dist: python-dateutil (<3,>=2.3)
Requires-Dist: prison (<1.0.0,>=0.2.1)
Requires-Dist: PyJWT (<2.0.0,>=1.7.1)
Requires-Dist: sqlalchemy-utils (<1,>=0.32.21)
Provides-Extra: jmespath
Requires-Dist: jmespath (>=0.9.5) ; extra == 'jmespath'
Provides-Extra: oauth
Requires-Dist: Authlib (<1.0.0,>=0.14) ; extra == 'oauth'
